fluxsave_sdk/__init__.py
fluxsave_sdk/client.py
fluxsave_sdk-0.1.1.dist-info/METADATA
fluxsave_sdk-0.1.1.dist-info/WHEEL
fluxsave_sdk-0.1.1.dist-info/top_level.txt
fluxsave_sdk-0.1.1.dist-info/RECORD
