Metadata-Version: 2.4
Name: fluxsave-sdk
Version: 0.1.1
Summary: FluxSave SDK for API key uploads and file management
Author: FluxSave
License-Expression: MIT
Project-URL: Homepage, https://fluxsave-sdk-docs.vercel.app/
Project-URL: Repository, https://github.com/fluxsave/fluxsave-sdk-python
Keywords: fluxsave,sdk,storage,upload
Classifier: Programming Language :: Python :: 3
Classifier: Operating System :: OS Independent
Requires-Python: >=3.9
Requires-Dist: requests>=2.31
